Workbook

Sheet Inputs
A1: Loan Profitability and Expected Loss Model
A2: Illustrative model of one amortizing loan: what the borrower pays, what the bank earns after funding, operating and credit costs, and the return on the capital held against it.
A3: Legend: blue text on yellow = assumption you can change. Black = formula. All figures are illustrative assumptions, not any bank's actual numbers.
A5: Assumption | B5: Value | C5: Notes
A6: Loan amount ($) | B6: 250000 | C6: Amount lent to the borrower (example value)
A7: Annual interest rate charged | B7: 0.075 | C7: Rate paid by the borrower, paid monthly
A8: Term (years, 1 to 10) | B8: 5 | C8: Schedule is monthly and holds up to 120 months
A9: Origination fee (% of loan) | B9: 0.01 | C9: Fee earned by the bank in month 1
A10: Cost of funds (annual) | B10: 0.05 | C10: What the bank pays to fund the loan (assumption)
A11: Operating cost (annual, % of balance) | B11: 0.006 | C11: Cost of servicing the loan (assumption)
A12: Probability of default, PD (annual) | B12: 0.015 | C12: Chance the borrower defaults in a year (assumption)
A13: Loss given default, LGD | B13: 0.45 | C13: Share of the balance lost if default happens (assumption)
A14: Capital held (% of balance) | B14: 0.08 | C14: Simplified capital buffer, not a regulatory formula
A15: Required return on capital (hurdle) | B15: 0.12 | C15: Minimum return the bank wants on its capital (assumption)
A16: Tax rate | B16: 0.26 | C16: Applied to pre-tax profit (assumption)
A18: Derived values
A19: Number of monthly payments | B19: =B8*12 -> 60
A20: Monthly interest rate | B20: =B7/12 -> 0.00625
A21: Monthly payment ($) | B21: =PMT(B20,B19,-B6) -> 5009.4871
A22: Origination fee income ($) | B22: =B6*B9 -> 2500

Sheet Summary
A1: Summary: Is this loan worth making?
A2: Results update automatically when you change the assumptions on the Inputs sheet.
A4: Borrower view | B4: Value
A5: Monthly payment | B5: =Inputs!$B$21 -> 5009.4871
A6: Total interest paid by borrower | B6: =Schedule!D126 -> 50569.229
A7: Total repaid (principal + interest) | B7: =Schedule!C126 -> 300569.23
A9: Bank view (over the life of the loan) | B9: Value
A10: Interest income | B10: =Schedule!D126 -> 50569.229
A11: Origination fee income | B11: =Inputs!$B$22 -> 2500
A12: Funding cost | B12: =-Schedule!G126 -> -33712.819
A13: Operating cost | B13: =-Schedule!H126 -> -4045.5383
A14: Expected credit loss | B14: =-Schedule!I126 -> -4551.2306
A15: Pre-tax profit | B15: =SUM(B10:B14) -> 10759.641
A16: Tax | B16: =-Schedule!K126 -> -2797.5066
A17: Net income | B17: =B15+B16 -> 7962.1341
A19: Risk and return | B19: Value
A20: Capital-years held (sum of monthly capital / 12) | B20: =SUM(Schedule!M5:M124)/12 -> 53940.511
A21: Return on capital (annualized) | B21: =IF(B20=0,0,B17/B20) -> 0.14760954
A22: Required return (hurdle) | B22: =Inputs!$B$15 -> 0.12
A23: Meets hurdle? | B23: =IF(B21>=B22,"Yes","No") -> Yes
A24: Economic profit (net income minus hurdle charge) | B24: =B17-B22*B20 -> 1489.2728
A25: Lifetime expected loss as % of loan | B25: =-B14/Inputs!$B$6 -> 0.018204922
A26: Break-even interest rate (covers funding, operating and expected loss costs) | B26: =Inputs!$B$10+Inputs!$B$11+Inputs!$B$12*Inputs!$B$13 -> 0.06275
A27: Rate charged minus break-even rate (annual margin) | B27: =Inputs!$B$7-B26 -> 0.01225
A28: Check: balance is zero at end of term | B28: =IF(ABS(INDEX(Schedule!F5:F124,Inputs!$B$19))<0.01,"OK","CHECK") -> OK
A30: How to read it: if return on capital is above the hurdle, the loan creates value. Raise the expected loss (PD or LGD) or cost of funds on the Inputs sheet and watch it fall below.

Sheet Schedule
A1: Monthly Loan Schedule and Bank Profitability
A2: All figures are formulas driven by the Inputs sheet. Rows after the loan is repaid show a dash.
A4: Month | B4: Opening balance | C4: Payment | D4: Interest | E4: Principal | F4: Closing balance | G4: Funding cost | H4: Operating cost | I4: Expected loss | J4: Pre-tax profit | K4: Tax | L4: Net income | M4: Capital held
A5: 1 | B5: =Inputs!$B$6 -> 250000 | C5: =IF(A5<=Inputs!$B$19,Inputs!$B$21,0) -> 5009.4871 | D5: =B5*Inputs!$B$20 -> 1562.5 | E5: =C5-D5 -> 3446.9871 | F5: =ROUND(B5-E5,6) -> 246553.01 | G5: =B5*Inputs!$B$10/12 -> 1041.6667 | H5: =B5*Inputs!$B$11/12 -> 125 | I5: =B5*Inputs!$B$12/12*Inputs!$B$13 -> 140.625 | J5: =D5-G5-H5-I5+IF(A5=1,Inputs!$B$22,0) -> 2755.2083 | K5: =J5*Inputs!$B$16 -> 716.35417 | L5: =J5-K5 -> 2038.8542 | M5: =B5*Inputs!$B$14 -> 20000
A6: 2 | B6: =F5 -> 246553.01 | C6: =IF(A6<=Inputs!$B$19,Inputs!$B$21,0) -> 5009.4871 | D6: =B6*Inputs!$B$20 -> 1540.9563 | E6: =C6-D6 -> 3468.5308 | F6: =ROUND(B6-E6,6) -> 243084.48 | G6: =B6*Inputs!$B$10/12 -> 1027.3042 | H6: =B6*Inputs!$B$11/12 -> 123.27651 | I6: =B6*Inputs!$B$12/12*Inputs!$B$13 -> 138.68607 | J6: =D6-G6-H6-I6+IF(A6=1,Inputs!$B$22,0) -> 251.68953 | K6: =J6*Inputs!$B$16 -> 65.439279 | L6: =J6-K6 -> 186.25026 | M6: =B6*Inputs!$B$14 -> 19724.241
A7: 3 | B7: =F6 -> 243084.48 | C7: =IF(A7<=Inputs!$B$19,Inputs!$B$21,0) -> 5009.4871 | D7: =B7*Inputs!$B$20 -> 1519.278 | E7: =C7-D7 -> 3490.2091 | F7: =ROUND(B7-E7,6) -> 239594.27 | G7: =B7*Inputs!$B$10/12 -> 1012.852 | H7: =B7*Inputs!$B$11/12 -> 121.54224 | I7: =B7*Inputs!$B$12/12*Inputs!$B$13 -> 136.73502 | J7: =D7-G7-H7-I7+IF(A7=1,Inputs!$B$22,0) -> 248.14874 | K7: =J7*Inputs!$B$16 -> 64.518673 | L7: =J7-K7 -> 183.63007 | M7: =B7*Inputs!$B$14 -> 19446.759
A8: 4 | B8: =F7 -> 239594.27 | C8: =IF(A8<=Inputs!$B$19,Inputs!$B$21,0) -> 5009.4871 | D8: =B8*Inputs!$B$20 -> 1497.4642 | E8: =C8-D8 -> 3512.0229 | F8: =ROUND(B8-E8,6) -> 236082.25 | G8: =B8*Inputs!$B$10/12 -> 998.30947 | H8: =B8*Inputs!$B$11/12 -> 119.79714 | I8: =B8*Inputs!$B$12/12*Inputs!$B$13 -> 134.77178 | J8: =D8-G8-H8-I8+IF(A8=1,Inputs!$B$22,0) -> 244.58582 | K8: =J8*Inputs!$B$16 -> 63.592313 | L8: =J8-K8 -> 180.99351 | M8: =B8*Inputs!$B$14 -> 19167.542
A9: 5 | B9: =F8 -> 236082.25 | C9: =IF(A9<=Inputs!$B$19,Inputs!$B$21,0) -> 5009.4871 | D9: =B9*Inputs!$B$20 -> 1475.5141 | E9: =C9-D9 -> 3533.9731 | F9: =ROUND(B9-E9,6) -> 232548.28 | G9: =B9*Inputs!$B$10/12 -> 983.67604 | H9: =B9*Inputs!$B$11/12 -> 118.04112 | I9: =B9*Inputs!$B$12/12*Inputs!$B$13 -> 132.79627 | J9: =D9-G9-H9-I9+IF(A9=1,Inputs!$B$22,0) -> 241.00063 | K9: =J9*Inputs!$B$16 -> 62.660164 | L9: =J9-K9 -> 178.34047 | M9: =B9*Inputs!$B$14 -> 18886.58
A10: 6 | B10: =F9 -> 232548.28 | C10: =IF(A10<=Inputs!$B$19,Inputs!$B$21,0) -> 5009.4871 | D10: =B10*Inputs!$B$20 -> 1453.4267 | E10: =C10-D10 -> 3556.0604 | F10: =ROUND(B10-E10,6) -> 228992.22 | G10: =B10*Inputs!$B$10/12 -> 968.95115 | H10: =B10*Inputs!$B$11/12 -> 116.27414 | I10: =B10*Inputs!$B$12/12*Inputs!$B$13 -> 130.80841 | J10: =D10-G10-H10-I10+IF(A10=1,Inputs!$B$22,0) -> 237.39303 | K10: =J10*Inputs!$B$16 -> 61.722188 | L10: =J10-K10 -> 175.67084 | M10: =B10*Inputs!$B$14 -> 18603.862
A11: 7 | B11: =F10 -> 228992.22 | C11: =IF(A11<=Inputs!$B$19,Inputs!$B$21,0) -> 5009.4871 | D11: =B11*Inputs!$B$20 -> 1431.2014 | E11: =C11-D11 -> 3578.2858 | F11: =ROUND(B11-E11,6) -> 225413.93 | G11: =B11*Inputs!$B$10/12 -> 954.13424 | H11: =B11*Inputs!$B$11/12 -> 114.49611 | I11: =B11*Inputs!$B$12/12*Inputs!$B$13 -> 128.80812 | J11: =D11-G11-H11-I11+IF(A11=1,Inputs!$B$22,0) -> 233.76289 | K11: =J11*Inputs!$B$16 -> 60.778351 | L11: =J11-K11 -> 172.98454 | M11: =B11*Inputs!$B$14 -> 18319.377
A12: 8 | B12: =F11 -> 225413.93 | C12: =IF(A12<=Inputs!$B$19,Inputs!$B$21,0) -> 5009.4871 | D12: =B12*Inputs!$B$20 -> 1408.8371 | E12: =C12-D12 -> 3600.6501 | F12: =ROUND(B12-E12,6) -> 221813.28 | G12: =B12*Inputs!$B$10/12 -> 939.22471 | H12: =B12*Inputs!$B$11/12 -> 112.70697 | I12: =B12*Inputs!$B$12/12*Inputs!$B$13 -> 126.79534 | J12: =D12-G12-H12-I12+IF(A12=1,Inputs!$B$22,0) -> 230.11005 | K12: =J12*Inputs!$B$16 -> 59.828614 | L12: =J12-K12 -> 170.28144 | M12: =B12*Inputs!$B$14 -> 18033.114
A13: 9 | B13: =F12 -> 221813.28 | C13: =IF(A13<=Inputs!$B$19,Inputs!$B$21,0) -> 5009.4871 | D13: =B13*Inputs!$B$20 -> 1386.333 | E13: =C13-D13 -> 3623.1541 | F13: =ROUND(B13-E13,6) -> 218190.13 | G13: =B13*Inputs!$B$10/12 -> 924.222 | H13: =B13*Inputs!$B$11/12 -> 110.90664 | I13: =B13*Inputs!$B$12/12*Inputs!$B$13 -> 124.76997 | J13: =D13-G13-H13-I13+IF(A13=1,Inputs!$B$22,0) -> 226.43439 | K13: =J13*Inputs!$B$16 -> 58.872942 | L13: =J13-K13 -> 167.56145 | M13: =B13*Inputs!$B$14 -> 17745.062
A14: 10 | B14: =F13 -> 218190.13 | C14: =IF(A14<=Inputs!$B$19,Inputs!$B$21,0) -> 5009.4871 | D14: =B14*Inputs!$B$20 -> 1363.6883 | E14: =C14-D14 -> 3645.7989 | F14: =ROUND(B14-E14,6) -> 214544.33 | G14: =B14*Inputs!$B$10/12 -> 909.12553 | H14: =B14*Inputs!$B$11/12 -> 109.09506 | I14: =B14*Inputs!$B$12/12*Inputs!$B$13 -> 122.73195 | J14: =D14-G14-H14-I14+IF(A14=1,Inputs!$B$22,0) -> 222.73575 | K14: =J14*Inputs!$B$16 -> 57.911296 | L14: =J14-K14 -> 164.82446 | M14: =B14*Inputs!$B$14 -> 17455.21
A15: 11 | B15: =F14 -> 214544.33 | C15: =IF(A15<=Inputs!$B$19,Inputs!$B$21,0) -> 5009.4871 | D15: =B15*Inputs!$B$20 -> 1340.902 | E15: =C15-D15 -> 3668.5851 | F15: =ROUND(B15-E15,6) -> 210875.74 | G15: =B15*Inputs!$B$10/12 -> 893.9347 | H15: =B15*Inputs!$B$11/12 -> 107.27216 | I15: =B15*Inputs!$B$12/12*Inputs!$B$13 -> 120.68118 | J15: =D15-G15-H15-I15+IF(A15=1,Inputs!$B$22,0) -> 219.014 | K15: =J15*Inputs!$B$16 -> 56.94364 | L15: =J15-K15 -> 162.07036 | M15: =B15*Inputs!$B$14 -> 17163.546
A16: 12 | B16: =F15 -> 210875.74 | C16: =IF(A16<=Inputs!$B$19,Inputs!$B$21,0) -> 5009.4871 | D16: =B16*Inputs!$B$20 -> 1317.9734 | E16: =C16-D16 -> 3691.5138 | F16: =ROUND(B16-E16,6) -> 207184.23 | G16: =B16*Inputs!$B$10/12 -> 878.64893 | H16: =B16*Inputs!$B$11/12 -> 105.43787 | I16: =B16*Inputs!$B$12/12*Inputs!$B$13 -> 118.61761 | J16: =D16-G16-H16-I16+IF(A16=1,Inputs!$B$22,0) -> 215.26899 | K16: =J16*Inputs!$B$16 -> 55.969937 | L16: =J16-K16 -> 159.29905 | M16: =B16*Inputs!$B$14 -> 16870.059
A17: 13 | B17: =F16 -> 207184.23 | C17: =IF(A17<=Inputs!$B$19,Inputs!$B$21,0) -> 5009.4871 | D17: =B17*Inputs!$B$20 -> 1294.9014 | E17: =C17-D17 -> 3714.5857 | F17: =ROUND(B17-E17,6) -> 203469.64 | G17: =B17*Inputs!$B$10/12 -> 863.26762 | H17: =B17*Inputs!$B$11/12 -> 103.59211 | I17: =B17*Inputs!$B$12/12*Inputs!$B$13 -> 116.54113 | J17: =D17-G17-H17-I17+IF(A17=1,Inputs!$B$22,0) -> 211.50057 | K17: =J17*Inputs!$B$16 -> 54.990147 | L17: =J17-K17 -> 156.51042 | M17: =B17*Inputs!$B$14 -> 16574.738
... A124: 120 | B124: =F123 -> 0 | C124: =IF(A124<=Inputs!$B$19,Inputs!$B$21,0) -> 0 | D124: =B124*Inputs!$B$20 -> 0 | E124: =C124-D124 -> 0 | F124: =ROUND(B124-E124,6) -> 0 | G124: =B124*Inputs!$B$10/12 -> 0 | H124: =B124*Inputs!$B$11/12 -> 0 | I124: =B124*Inputs!$B$12/12*Inputs!$B$13 -> 0 | J124: =D124-G124-H124-I124+IF(A124=1,Inputs!$B$22,0) -> 0 | K124: =J124*Inputs!$B$16 -> 0 | L124: =J124-K124 -> 0 | M124: =B124*Inputs!$B$14 -> 0
A126: Total | C126: =SUM(C5:C124) -> 300569.23 | D126: =SUM(D5:D124) -> 50569.229 | E126: =SUM(E5:E124) -> 250000 | G126: =SUM(G5:G124) -> 33712.819 | H126: =SUM(H5:H124) -> 4045.5383 | I126: =SUM(I5:I124) -> 4551.2306 | J126: =SUM(J5:J124) -> 10759.641 | K126: =SUM(K5:K124) -> 2797.5066 | L126: =SUM(L5:L124) -> 7962.1341

Sheet Sensitivity
A1: Sensitivity Analysis
A2: Table 1: monthly payment for different rates and terms. Table 2: annual risk-adjusted margin for different rates and default probabilities (approximate, on the average balance, before fee and tax).
A4: Table 1: Monthly payment ($) by interest rate (rows) and term in years (columns)
A5: Rate / Term | B5: 1 | C5: 2 | D5: 3 | E5: 4 | F5: 5 | G5: 7 | H5: 10
A6: 0.05 | B6: =PMT($A6/12,B$5*12,-Inputs!$B$6) -> 21401.87 | C6: =PMT($A6/12,C$5*12,-Inputs!$B$6) -> 10967.847 | D6: =PMT($A6/12,D$5*12,-Inputs!$B$6) -> 7492.7243 | E6: =PMT($A6/12,E$5*12,-Inputs!$B$6) -> 5757.3234 | F6: =PMT($A6/12,F$5*12,-Inputs!$B$6) -> 4717.8084 | G6: =PMT($A6/12,G$5*12,-Inputs!$B$6) -> 3533.4773 | H6: =PMT($A6/12,H$5*12,-Inputs!$B$6) -> 2651.6379
A7: 0.055 | B7: =PMT($A7/12,B$5*12,-Inputs!$B$6) -> 21459.196 | C7: =PMT($A7/12,C$5*12,-Inputs!$B$6) -> 11023.914 | D7: =PMT($A7/12,D$5*12,-Inputs!$B$6) -> 7548.9755 | E7: =PMT($A7/12,E$5*12,-Inputs!$B$6) -> 5814.1188 | F7: =PMT($A7/12,F$5*12,-Inputs!$B$6) -> 4775.2905 | G7: =PMT($A7/12,G$5*12,-Inputs!$B$6) -> 3592.5107 | H7: =PMT($A7/12,H$5*12,-Inputs!$B$6) -> 2713.1569
A8: 0.06 | B8: =PMT($A8/12,B$5*12,-Inputs!$B$6) -> 21516.607 | C8: =PMT($A8/12,C$5*12,-Inputs!$B$6) -> 11080.153 | D8: =PMT($A8/12,D$5*12,-Inputs!$B$6) -> 7605.4844 | E8: =PMT($A8/12,E$5*12,-Inputs!$B$6) -> 5871.2573 | F8: =PMT($A8/12,F$5*12,-Inputs!$B$6) -> 4833.2004 | G8: =PMT($A8/12,G$5*12,-Inputs!$B$6) -> 3652.1386 | H8: =PMT($A8/12,H$5*12,-Inputs!$B$6) -> 2775.5125
A9: 0.065 | B9: =PMT($A9/12,B$5*12,-Inputs!$B$6) -> 21574.104 | C9: =PMT($A9/12,C$5*12,-Inputs!$B$6) -> 11136.563 | D9: =PMT($A9/12,D$5*12,-Inputs!$B$6) -> 7662.2507 | E9: =PMT($A9/12,E$5*12,-Inputs!$B$6) -> 5928.7382 | F9: =PMT($A9/12,F$5*12,-Inputs!$B$6) -> 4891.5371 | G9: =PMT($A9/12,G$5*12,-Inputs!$B$6) -> 3712.3591 | H9: =PMT($A9/12,H$5*12,-Inputs!$B$6) -> 2838.6994
A10: 0.07 | B10: =PMT($A10/12,B$5*12,-Inputs!$B$6) -> 21631.687 | C10: =PMT($A10/12,C$5*12,-Inputs!$B$6) -> 11193.145 | D10: =PMT($A10/12,D$5*12,-Inputs!$B$6) -> 7719.2742 | E10: =PMT($A10/12,E$5*12,-Inputs!$B$6) -> 5986.5612 | F10: =PMT($A10/12,F$5*12,-Inputs!$B$6) -> 4950.2996 | G10: =PMT($A10/12,G$5*12,-Inputs!$B$6) -> 3773.17 | H10: =PMT($A10/12,H$5*12,-Inputs!$B$6) -> 2902.712
A11: 0.075 | B11: =PMT($A11/12,B$5*12,-Inputs!$B$6) -> 21689.354 | C11: =PMT($A11/12,C$5*12,-Inputs!$B$6) -> 11249.898 | D11: =PMT($A11/12,D$5*12,-Inputs!$B$6) -> 7776.5545 | E11: =PMT($A11/12,E$5*12,-Inputs!$B$6) -> 6044.7255 | F11: =PMT($A11/12,F$5*12,-Inputs!$B$6) -> 5009.4871 | G11: =PMT($A11/12,G$5*12,-Inputs!$B$6) -> 3834.569 | H11: =PMT($A11/12,H$5*12,-Inputs!$B$6) -> 2967.5442
A12: 0.08 | B12: =PMT($A12/12,B$5*12,-Inputs!$B$6) -> 21747.107 | C12: =PMT($A12/12,C$5*12,-Inputs!$B$6) -> 11306.823 | D12: =PMT($A12/12,D$5*12,-Inputs!$B$6) -> 7834.0914 | E12: =PMT($A12/12,E$5*12,-Inputs!$B$6) -> 6103.2306 | F12: =PMT($A12/12,F$5*12,-Inputs!$B$6) -> 5069.0986 | G12: =PMT($A12/12,G$5*12,-Inputs!$B$6) -> 3896.5536 | H12: =PMT($A12/12,H$5*12,-Inputs!$B$6) -> 3033.1899
A13: 0.085 | B13: =PMT($A13/12,B$5*12,-Inputs!$B$6) -> 21804.946 | C13: =PMT($A13/12,C$5*12,-Inputs!$B$6) -> 11363.919 | D13: =PMT($A13/12,D$5*12,-Inputs!$B$6) -> 7891.8844 | E13: =PMT($A13/12,E$5*12,-Inputs!$B$6) -> 6162.0758 | F13: =PMT($A13/12,F$5*12,-Inputs!$B$6) -> 5129.1328 | G13: =PMT($A13/12,G$5*12,-Inputs!$B$6) -> 3959.1214 | H13: =PMT($A13/12,H$5*12,-Inputs!$B$6) -> 3099.6422
A14: 0.09 | B14: =PMT($A14/12,B$5*12,-Inputs!$B$6) -> 21862.869 | C14: =PMT($A14/12,C$5*12,-Inputs!$B$6) -> 11421.186 | D14: =PMT($A14/12,D$5*12,-Inputs!$B$6) -> 7949.9332 | E14: =PMT($A14/12,E$5*12,-Inputs!$B$6) -> 6221.2606 | F14: =PMT($A14/12,F$5*12,-Inputs!$B$6) -> 5189.5888 | G14: =PMT($A14/12,G$5*12,-Inputs!$B$6) -> 4022.2696 | H14: =PMT($A14/12,H$5*12,-Inputs!$B$6) -> 3166.8943
A15: 0.095 | B15: =PMT($A15/12,B$5*12,-Inputs!$B$6) -> 21920.878 | C15: =PMT($A15/12,C$5*12,-Inputs!$B$6) -> 11478.623 | D15: =PMT($A15/12,D$5*12,-Inputs!$B$6) -> 8008.2374 | E15: =PMT($A15/12,E$5*12,-Inputs!$B$6) -> 6280.7842 | F15: =PMT($A15/12,F$5*12,-Inputs!$B$6) -> 5250.4653 | G15: =PMT($A15/12,G$5*12,-Inputs!$B$6) -> 4085.9954 | H15: =PMT($A15/12,H$5*12,-Inputs!$B$6) -> 3234.9389
A16: 0.1 | B16: =PMT($A16/12,B$5*12,-Inputs!$B$6) -> 21978.972 | C16: =PMT($A16/12,C$5*12,-Inputs!$B$6) -> 11536.232 | D16: =PMT($A16/12,D$5*12,-Inputs!$B$6) -> 8066.7968 | E16: =PMT($A16/12,E$5*12,-Inputs!$B$6) -> 6340.6459 | F16: =PMT($A16/12,F$5*12,-Inputs!$B$6) -> 5311.7612 | G16: =PMT($A16/12,G$5*12,-Inputs!$B$6) -> 4150.296 | H16: =PMT($A16/12,H$5*12,-Inputs!$B$6) -> 3303.7684
A19: Table 2: Annual risk-adjusted margin by interest rate (rows) and probability of default (columns)
A20: Rate / PD | B20: 0.005 | C20: 0.01 | D20: 0.015 | E20: 0.02 | F20: 0.03 | G20: 0.04 | H20: 0.05
A21: 0.05 | B21: =$A21-Inputs!$B$10-Inputs!$B$11-B$20*Inputs!$B$13 -> -0.00825 | C21: =$A21-Inputs!$B$10-Inputs!$B$11-C$20*Inputs!$B$13 -> -0.0105 | D21: =$A21-Inputs!$B$10-Inputs!$B$11-D$20*Inputs!$B$13 -> -0.01275 | E21: =$A21-Inputs!$B$10-Inputs!$B$11-E$20*Inputs!$B$13 -> -0.015 | F21: =$A21-Inputs!$B$10-Inputs!$B$11-F$20*Inputs!$B$13 -> -0.0195 | G21: =$A21-Inputs!$B$10-Inputs!$B$11-G$20*Inputs!$B$13 -> -0.024 | H21: =$A21-Inputs!$B$10-Inputs!$B$11-H$20*Inputs!$B$13 -> -0.0285
A22: 0.055 | B22: =$A22-Inputs!$B$10-Inputs!$B$11-B$20*Inputs!$B$13 -> -0.00325 | C22: =$A22-Inputs!$B$10-Inputs!$B$11-C$20*Inputs!$B$13 -> -0.0055 | D22: =$A22-Inputs!$B$10-Inputs!$B$11-D$20*Inputs!$B$13 -> -0.00775 | E22: =$A22-Inputs!$B$10-Inputs!$B$11-E$20*Inputs!$B$13 -> -0.01 | F22: =$A22-Inputs!$B$10-Inputs!$B$11-F$20*Inputs!$B$13 -> -0.0145 | G22: =$A22-Inputs!$B$10-Inputs!$B$11-G$20*Inputs!$B$13 -> -0.019 | H22: =$A22-Inputs!$B$10-Inputs!$B$11-H$20*Inputs!$B$13 -> -0.0235
A23: 0.06 | B23: =$A23-Inputs!$B$10-Inputs!$B$11-B$20*Inputs!$B$13 -> 0.00175 | C23: =$A23-Inputs!$B$10-Inputs!$B$11-C$20*Inputs!$B$13 -> -0.0005 | D23: =$A23-Inputs!$B$10-Inputs!$B$11-D$20*Inputs!$B$13 -> -0.00275 | E23: =$A23-Inputs!$B$10-Inputs!$B$11-E$20*Inputs!$B$13 -> -0.005 | F23: =$A23-Inputs!$B$10-Inputs!$B$11-F$20*Inputs!$B$13 -> -0.0095 | G23: =$A23-Inputs!$B$10-Inputs!$B$11-G$20*Inputs!$B$13 -> -0.014 | H23: =$A23-Inputs!$B$10-Inputs!$B$11-H$20*Inputs!$B$13 -> -0.0185
A24: 0.065 | B24: =$A24-Inputs!$B$10-Inputs!$B$11-B$20*Inputs!$B$13 -> 0.00675 | C24: =$A24-Inputs!$B$10-Inputs!$B$11-C$20*Inputs!$B$13 -> 0.0045 | D24: =$A24-Inputs!$B$10-Inputs!$B$11-D$20*Inputs!$B$13 -> 0.00225 | E24: =$A24-Inputs!$B$10-Inputs!$B$11-E$20*Inputs!$B$13 -> 0 | F24: =$A24-Inputs!$B$10-Inputs!$B$11-F$20*Inputs!$B$13 -> -0.0045 | G24: =$A24-Inputs!$B$10-Inputs!$B$11-G$20*Inputs!$B$13 -> -0.009 | H24: =$A24-Inputs!$B$10-Inputs!$B$11-H$20*Inputs!$B$13 -> -0.0135
A25: 0.07 | B25: =$A25-Inputs!$B$10-Inputs!$B$11-B$20*Inputs!$B$13 -> 0.01175 | C25: =$A25-Inputs!$B$10-Inputs!$B$11-C$20*Inputs!$B$13 -> 0.0095 | D25: =$A25-Inputs!$B$10-Inputs!$B$11-D$20*Inputs!$B$13 -> 0.00725 | E25: =$A25-Inputs!$B$10-Inputs!$B$11-E$20*Inputs!$B$13 -> 0.005 | F25: =$A25-Inputs!$B$10-Inputs!$B$11-F$20*Inputs!$B$13 -> 0.0005 | G25: =$A25-Inputs!$B$10-Inputs!$B$11-G$20*Inputs!$B$13 -> -0.004 | H25: =$A25-Inputs!$B$10-Inputs!$B$11-H$20*Inputs!$B$13 -> -0.0085
A26: 0.075 | B26: =$A26-Inputs!$B$10-Inputs!$B$11-B$20*Inputs!$B$13 -> 0.01675 | C26: =$A26-Inputs!$B$10-Inputs!$B$11-C$20*Inputs!$B$13 -> 0.0145 | D26: =$A26-Inputs!$B$10-Inputs!$B$11-D$20*Inputs!$B$13 -> 0.01225 | E26: =$A26-Inputs!$B$10-Inputs!$B$11-E$20*Inputs!$B$13 -> 0.01 | F26: =$A26-Inputs!$B$10-Inputs!$B$11-F$20*Inputs!$B$13 -> 0.0055 | G26: =$A26-Inputs!$B$10-Inputs!$B$11-G$20*Inputs!$B$13 -> 0.001 | H26: =$A26-Inputs!$B$10-Inputs!$B$11-H$20*Inputs!$B$13 -> -0.0035
A27: 0.08 | B27: =$A27-Inputs!$B$10-Inputs!$B$11-B$20*Inputs!$B$13 -> 0.02175 | C27: =$A27-Inputs!$B$10-Inputs!$B$11-C$20*Inputs!$B$13 -> 0.0195 | D27: =$A27-Inputs!$B$10-Inputs!$B$11-D$20*Inputs!$B$13 -> 0.01725 | E27: =$A27-Inputs!$B$10-Inputs!$B$11-E$20*Inputs!$B$13 -> 0.015 | F27: =$A27-Inputs!$B$10-Inputs!$B$11-F$20*Inputs!$B$13 -> 0.0105 | G27: =$A27-Inputs!$B$10-Inputs!$B$11-G$20*Inputs!$B$13 -> 0.006 | H27: =$A27-Inputs!$B$10-Inputs!$B$11-H$20*Inputs!$B$13 -> 0.0015
A28: 0.085 | B28: =$A28-Inputs!$B$10-Inputs!$B$11-B$20*Inputs!$B$13 -> 0.02675 | C28: =$A28-Inputs!$B$10-Inputs!$B$11-C$20*Inputs!$B$13 -> 0.0245 | D28: =$A28-Inputs!$B$10-Inputs!$B$11-D$20*Inputs!$B$13 -> 0.02225 | E28: =$A28-Inputs!$B$10-Inputs!$B$11-E$20*Inputs!$B$13 -> 0.02 | F28: =$A28-Inputs!$B$10-Inputs!$B$11-F$20*Inputs!$B$13 -> 0.0155 | G28: =$A28-Inputs!$B$10-Inputs!$B$11-G$20*Inputs!$B$13 -> 0.011 | H28: =$A28-Inputs!$B$10-Inputs!$B$11-H$20*Inputs!$B$13 -> 0.0065
A29: 0.09 | B29: =$A29-Inputs!$B$10-Inputs!$B$11-B$20*Inputs!$B$13 -> 0.03175 | C29: =$A29-Inputs!$B$10-Inputs!$B$11-C$20*Inputs!$B$13 -> 0.0295 | D29: =$A29-Inputs!$B$10-Inputs!$B$11-D$20*Inputs!$B$13 -> 0.02725 | E29: =$A29-Inputs!$B$10-Inputs!$B$11-E$20*Inputs!$B$13 -> 0.025 | F29: =$A29-Inputs!$B$10-Inputs!$B$11-F$20*Inputs!$B$13 -> 0.0205 | G29: =$A29-Inputs!$B$10-Inputs!$B$11-G$20*Inputs!$B$13 -> 0.016 | H29: =$A29-Inputs!$B$10-Inputs!$B$11-H$20*Inputs!$B$13 -> 0.0115
A30: 0.095 | B30: =$A30-Inputs!$B$10-Inputs!$B$11-B$20*Inputs!$B$13 -> 0.03675 | C30: =$A30-Inputs!$B$10-Inputs!$B$11-C$20*Inputs!$B$13 -> 0.0345 | D30: =$A30-Inputs!$B$10-Inputs!$B$11-D$20*Inputs!$B$13 -> 0.03225 | E30: =$A30-Inputs!$B$10-Inputs!$B$11-E$20*Inputs!$B$13 -> 0.03 | F30: =$A30-Inputs!$B$10-Inputs!$B$11-F$20*Inputs!$B$13 -> 0.0255 | G30: =$A30-Inputs!$B$10-Inputs!$B$11-G$20*Inputs!$B$13 -> 0.021 | H30: =$A30-Inputs!$B$10-Inputs!$B$11-H$20*Inputs!$B$13 -> 0.0165
A31: 0.1 | B31: =$A31-Inputs!$B$10-Inputs!$B$11-B$20*Inputs!$B$13 -> 0.04175 | C31: =$A31-Inputs!$B$10-Inputs!$B$11-C$20*Inputs!$B$13 -> 0.0395 | D31: =$A31-Inputs!$B$10-Inputs!$B$11-D$20*Inputs!$B$13 -> 0.03725 | E31: =$A31-Inputs!$B$10-Inputs!$B$11-E$20*Inputs!$B$13 -> 0.035 | F31: =$A31-Inputs!$B$10-Inputs!$B$11-F$20*Inputs!$B$13 -> 0.0305 | G31: =$A31-Inputs!$B$10-Inputs!$B$11-G$20*Inputs!$B$13 -> 0.026 | H31: =$A31-Inputs!$B$10-Inputs!$B$11-H$20*Inputs!$B$13 -> 0.0215
A33: Margin = interest rate - cost of funds - operating cost - (PD x LGD). Green = positive margin, red = the loan loses money before capital costs.
